odoo/addons/auth_totp_password_security/README.rst
odoo/addons/auth_totp_password_security/__init__.py
odoo/addons/auth_totp_password_security/__manifest__.py
odoo/addons/auth_totp_password_security/controllers/__init__.py
odoo/addons/auth_totp_password_security/controllers/main.py
odoo/addons/auth_totp_password_security/tests/__init__.py
odoo/addons/auth_totp_password_security/tests/test_main.py
odoo11_addon_auth_totp_password_security-11.0.1.0.0.dist-info/DESCRIPTION.rst
odoo11_addon_auth_totp_password_security-11.0.1.0.0.dist-info/METADATA
odoo11_addon_auth_totp_password_security-11.0.1.0.0.dist-info/RECORD
odoo11_addon_auth_totp_password_security-11.0.1.0.0.dist-info/WHEEL
odoo11_addon_auth_totp_password_security-11.0.1.0.0.dist-info/metadata.json
odoo11_addon_auth_totp_password_security-11.0.1.0.0.dist-info/top_level.txt
